[{"name":"TARA GOLD RESOURCES CORP.","cik":1100747,"fy":2011,"cl":2,"nm":-16.0,"pe":null,"pb":2.9209772401718923,"rg":null,"rev":160000.0,"ni":-2560000.0,"ast":18926000.0,"eq":12566000.0,"oc":-3789000.0,"roe":-0.20372433550851504,"de":0.005491007480502945,"mdp":3.5772684626725644,"ux":9.090864181518555,"uy":-2.08252215385437,"devs":{"Scale":0.02647919813238902,"Float":0.49587701965671177,"Margin":-1.776356839400219e-14,"OpMargin":-0.12443473189909049,"Growth":0.050895216340881566,"Leverage":-0.17916301640290863,"ROE":0.25671874755368435,"CashYld":-0.3143860200349698}},{"name":"TARA GOLD RESOURCES CORP.","cik":1100747,"fy":2012,"cl":-1,"nm":null,"pe":null,"pb":0.0,"rg":null,"rev":null,"ni":-3100000.0,"ast":16750000.0,"eq":10854000.0,"oc":-5751000.0,"roe":-0.28560899207665374,"de":0.1691542288557214,"mdp":null,"ux":null,"uy":null,"devs":{"Scale":null,"Float":null,"Margin":null,"OpMargin":null,"Growth":null,"Leverage":null,"ROE":null,"CashYld":null}},{"name":"TARA GOLD RESOURCES CORP.","cik":1100747,"fy":2013,"cl":-1,"nm":null,"pe":null,"pb":0.0,"rg":null,"rev":null,"ni":-3913000.0,"ast":8105000.0,"eq":5143000.0,"oc":-3482000.0,"roe":-0.7608399766673148,"de":0.05677620066109275,"mdp":null,"ux":null,"uy":null,"devs":{"Scale":null,"Float":null,"Margin":null,"OpMargin":null,"Growth":null,"Leverage":null,"ROE":null,"CashYld":null}},{"name":"TARA GOLD RESOURCES CORP.","cik":1100747,"fy":2014,"cl":-1,"nm":null,"pe":0.0,"pb":null,"rg":null,"rev":null,"ni":15227357.0,"ast":6432.0,"eq":-112277.0,"oc":-220852.0,"roe":-135.62311960597452,"de":-0.24942775457128352,"mdp":null,"ux":null,"uy":null,"devs":{"Scale":null,"Float":null,"Margin":null,"OpMargin":null,"Growth":null,"Leverage":null,"ROE":null,"CashYld":null}}]