[{"name":"SOUNDSTORM DIGITAL, INC.","cik":1572422,"fy":2013,"cl":-1,"nm":null,"pe":null,"pb":null,"rg":null,"rev":null,"ni":-62443.0,"ast":22746.0,"eq":-1598.0,"oc":-57657.0,"roe":39.075719649561954,"de":-0.0,"mdp":null,"ux":null,"uy":null,"devs":{"Scale":null,"Float":null,"Margin":null,"OpMargin":null,"Growth":null,"Leverage":null,"ROE":null,"CashYld":null}},{"name":"SOUNDSTORM DIGITAL, INC.","cik":1572422,"fy":2014,"cl":1,"nm":null,"pe":null,"pb":null,"rg":null,"rev":null,"ni":-54975.0,"ast":3132.0,"eq":-56573.0,"oc":-15351.0,"roe":0.9717533098828063,"de":-0.0,"mdp":1.45556895858464,"ux":3.3884990215301514,"uy":-5.997914791107178,"devs":{"Scale":0.0,"Float":-0.138895165511969,"Margin":0.0,"OpMargin":0.0,"Growth":0.0,"Leverage":-0.0,"ROE":-0.08501613913084725,"CashYld":0.4730585280060386}}]