[{"name":"Excellerant, Inc.","cik":1786119,"fy":2020,"cl":-1,"nm":null,"pe":null,"pb":null,"rg":null,"rev":0.0,"ni":-26344.0,"ast":20745.0,"eq":-6087.0,"oc":-14344.0,"roe":4.327911943486118,"de":-0.0,"mdp":null,"ux":null,"uy":null,"devs":{"Scale":null,"Float":null,"Margin":null,"OpMargin":null,"Growth":null,"Leverage":null,"ROE":null,"CashYld":null}},{"name":"Excellerant, Inc.","cik":1786119,"fy":2021,"cl":1,"nm":null,"pe":null,"pb":null,"rg":null,"rev":null,"ni":-13800.0,"ast":0.0,"eq":-19887.0,"oc":-34680.0,"roe":0.6939206516820033,"de":-0.0,"mdp":0.8939820399410267,"ux":2.8496999740600586,"uy":-6.250399112701416,"devs":{"Scale":0.21762596225713746,"Float":0.03993744008872038,"Margin":0.12641279920479567,"OpMargin":0.16089382785396095,"Growth":0.27108569868768795,"Leverage":-0.0,"ROE":-0.02478895634892302,"CashYld":0.10779305706008083}}]